dnastack/__init__.py
dnastack/__main__.py
dnastack/constants.py
dnastack/feature_flags.py
dnastack/json_path.py
dnastack/omics_cli.py
dnastack/alpha/__init__.py
dnastack/alpha/app/__init__.py
dnastack/alpha/app/explorer.py
dnastack/alpha/app/publisher.py
dnastack/alpha/app/workbench.py
dnastack/alpha/app/publisher_helper/__init__.py
dnastack/alpha/app/publisher_helper/collection_service.py
dnastack/alpha/app/publisher_helper/data_connect.py
dnastack/alpha/app/publisher_helper/exceptions.py
dnastack/alpha/app/publisher_helper/filter.py
dnastack/alpha/app/publisher_helper/models.py
dnastack/alpha/cli/__init__.py
dnastack/alpha/cli/auth.py
dnastack/alpha/cli/collections.py
dnastack/alpha/cli/commands.py
dnastack/alpha/cli/data_connect.py
dnastack/alpha/cli/wes.py
dnastack/alpha/cli/workflow_param_parser.py
dnastack/alpha/client/__init__.py
dnastack/alpha/client/collections/__init__.py
dnastack/alpha/client/collections/client.py
dnastack/alpha/client/wes/__init__.py
dnastack/alpha/client/wes/client.py
dnastack/cli/__init__.py
dnastack/cli/commands/__init__.py
dnastack/cli/commands/utils.py
dnastack/cli/commands/auth/__init__.py
dnastack/cli/commands/auth/commands.py
dnastack/cli/commands/auth/event_handlers.py
dnastack/cli/commands/collections/__init__.py
dnastack/cli/commands/collections/commands.py
dnastack/cli/commands/collections/tables.py
dnastack/cli/commands/collections/utils.py
dnastack/cli/commands/config/__init__.py
dnastack/cli/commands/config/commands.py
dnastack/cli/commands/config/contexts.py
dnastack/cli/commands/config/endpoints.py
dnastack/cli/commands/config/registries.py
dnastack/cli/commands/dataconnect/__init__.py
dnastack/cli/commands/dataconnect/commands.py
dnastack/cli/commands/dataconnect/tables.py
dnastack/cli/commands/dataconnect/utils.py
dnastack/cli/commands/drs/__init__.py
dnastack/cli/commands/drs/commands.py
dnastack/cli/commands/drs/utils.py
dnastack/cli/commands/explorer/__init__.py
dnastack/cli/commands/explorer/commands.py
dnastack_client_library-3.1.212.dist-info/licenses/LICENSE
dnastack_client_library-3.1.212.dist-info/METADATA
dnastack_client_library-3.1.212.dist-info/WHEEL
dnastack_client_library-3.1.212.dist-info/entry_points.txt
dnastack_client_library-3.1.212.dist-info/top_level.txt
dnastack_client_library-3.1.212.dist-info/RECORD
